pytest_discord/__init__.py
pytest_discord/__version__.py
pytest_discord/_const.py
pytest_discord/_opt_retriever.py
pytest_discord/plugin.py
pytest_discord-0.2.0.dist-info/LICENSE
pytest_discord-0.2.0.dist-info/METADATA
pytest_discord-0.2.0.dist-info/WHEEL
pytest_discord-0.2.0.dist-info/entry_points.txt
pytest_discord-0.2.0.dist-info/top_level.txt
pytest_discord-0.2.0.dist-info/RECORD
