Metadata-Version: 2.1
Name: pytest-discord
Version: 0.2.0
Summary: A pytest plugin to notify test results to a Discord channel.
Home-page: https://github.com/thombashi/pytest-discord
Author: Tsuyoshi Hombashi
Author-email: tsuyoshi.hombashi@gmail.com
License: MIT License
Project-URL: Changelog, https://github.com/thombashi/pytest-discord/releases
Project-URL: Source, https://github.com/thombashi/pytest-discord
Project-URL: Tracker, https://github.com/thombashi/pytest-discord/issues
Keywords: discord,plugin,pytest
Classifier: Development Status :: 4 - Beta
Classifier: Environment :: Plugins
Classifier: Framework :: Pytest
Classifier: Intended Audience :: Information Technology
Classifier: Intended Audience :: Developers
Classifier: License :: OSI Approved :: MIT License
Classifier: Operating System :: OS Independent
Classifier: Programming Language :: Python :: 3
Classifier: Programming Language :: Python :: 3.8
Classifier: Programming Language :: Python :: 3.9
Classifier: Programming Language :: Python :: 3.10
Classifier: Programming Language :: Python :: 3.11
Classifier: Programming Language :: Python :: 3.12
Classifier: Programming Language :: Python :: 3 :: Only
Classifier: Programming Language :: Python :: Implementation :: CPython
Classifier: Programming Language :: Python :: Implementation :: PyPy
Classifier: Topic :: Communications :: Chat
Classifier: Topic :: Software Development :: Testing
Requires-Python: >=3.8
License-File: LICENSE
Requires-Dist: aiohttp <4,>=3.6
Requires-Dist: discord.py <3,>=2
Requires-Dist: pathvalidate <4,>=2.5.2
Requires-Dist: pytest !=6.0.0,<9,>=3.3.2
Requires-Dist: pytest-md-report <1,>=0.6.1
Requires-Dist: typepy <2,>=1.1.4
Provides-Extra: test
Requires-Dist: mock ; extra == 'test'
